ign/__init__.py
ign/__main__.py
ign/_logging.py
ign/consts.py
ign/net.py
ign/utils.py
ign-0.1.1.dist-info/entry_points.txt
ign-0.1.1.dist-info/WHEEL
ign-0.1.1.dist-info/METADATA
ign-0.1.1.dist-info/RECORD
