Metadata-Version: 2.4
Name: ign
Version: 0.1.1
Summary: A tool for composing and synchronizing .gitignore from GitHub's template collection.
Author-email: Eugene Kim <ab@astral.blue>
Requires-Python: >=3.10
License-Expression: MIT
Classifier: Development Status :: 3 - Alpha
Classifier: Intended Audience :: Developers
Classifier: Programming Language :: Python :: 3
Classifier: Programming Language :: Python :: 3.9
Classifier: Programming Language :: Python :: 3.10
Classifier: Programming Language :: Python :: 3.11
Classifier: Programming Language :: Python :: 3.12
Classifier: Programming Language :: Python :: 3.13
Requires-Dist: async-lru>=2.0.5
Requires-Dist: httpx>=0.28.1
Requires-Dist: patch-ng>=1.18.1
Requires-Dist: pygithub>=2.6.1
Requires-Dist: python-dotenv>=1.1.1
Requires-Dist: python-json-logger>=3.3.0
Requires-Dist: rich>=14.0.0
Requires-Dist: flit>=3.12.0 ; extra == "build"
Requires-Dist: sphinx ; extra == "docs"
Requires-Dist: sphinx-rtd-theme ; extra == "docs"
Project-URL: Homepage, https://github.com/astralblue/ign
Project-URL: Issues, https://github.com/astralblue/ign/issues
Project-URL: Repository, https://github.com/astralblue/ign
Provides-Extra: build
Provides-Extra: docs
